Workbook

Sheet company data
A1: financial year | B1: Kind of packing | C1: type of container | D1: terms of delivery | E1: terms of payment
A2: 25-26 | B2: Wooden Crate packing | C2: FCL | D2: FOB | E2: 30 % Advance, Remaning Against Document
B3: Loose packing | D3: CIF | E3: 100 % Advance
B4: American Standard | D4: CNF | E4: 70 % Advance, Remaning Against Document
E5: 100% Against Documents
E6: LC at Sight

Sheet input data
A1: Financial Year | B1: 25-26
A2: No. | B2: 33
A3: Invoice Number | B3: ="BK0" & B2 & "/" & B1 -> BK033/25-26
A4: Date | B4: 45983
A5: LUT No: | B5: =IF(B1="24-25","AD240424008317F",IF(B1="23-24","AD240322004861M",IF(B1="25-26","AD2403250650768",IF(B1="","select the financial year")))) -> AD2403250650768
A6: CONSIGNEE | B6: To the Order
A7: Party Name | B7: HOANG MINH STONE TRADING COMPANY LIMITED Lot 175 MBQH 6804 Hac Thanh Ward, Thanh Hoa Province Tax ID: 2803146553 TEL: 0392794691 hoangminh6868vn@gmail.com
A13: number of containers | B13: 1
A14: Kind of Packing | B14: Loose packing
A15: Type of container | B15: FCL
A16: Terms of delivery | B16: CNF
A17: Terms of payment | B17: 100% Against Documents
A18: Product Name | B18: NATURAL POLISHED GRANITE SLABS
A19: Place Of Receipt By Pre-Carrier | B19: CHENNAI
A20: Port Of Loading | B20: CHENNAI
A21: Port Of Discharge | B21: HAI PHONG
A22: Place Of Delivery | B22: HAI PHONG
A23: Country Of Final Destination | B23: VIETNAM
A24: Container No. | B24: WHSU0423098
A25: Slabs | B25: 480
A26: Quantity | B26: 400
A27: Rate Per | B27: 23

Sheet Invoice
A1: INVOICE
A3: EXPORTER | E3: INVOICE NO. | H3: DATE
A4: B K EXPORTS | E4: ='input data'!B3 -> BK033/25-26 | H4: ='input data'!B4 -> 45983
A5: 90, Jasodanagar Cross Road, Nr. Canal, | E5: BUYER'S ORDER NO. | H5: LUT/ARN NO.
A6: Opp.Baroda Express Highway, Amraiwadi, | H6: ='input data'!B5 -> AD2403250650768
A7: Ahmedabad, Gujarat, India - 380026. | E7: PAN NO. /IEC CODE | H7: GSTIN
A8: +91 9313035076, +91 9537651265 | E8: AGQPJ1643Q | H8: 24AGQPJ1643Q1ZW
A9: info@bkexportsinternational.com | E9: KIND OF PACKING | H9: TYPE OF CONTAINER
A10: www.bkexportsinternational.com | E10: ='input data'!B14 -> Loose packing | H10: ='input data'!B13 & " " & 'input data'!B15 -> 1 FCL
A11: CONSIGNEE | E11: TERMS OF DELIVERY | H11: TERMS OF PAYMENT
A12: ='input data'!B6 -> To the Order | E12: ='input data'!B16 -> CNF | H12: ='input data'!B17 -> 100% Against Documents
A14: NOTIFY PARTY | E14: BANK DETAILS: ACCOUNT NAME : B K EXPORTS BANK NAME : BANK OF BARODA ACCOUNT NUMBER : 14970200000658 SWIFT CODE : BARBINBBVAT IFSC CODE : BARB0MANEAS (fifth digit zero) BRANCH : MANINAGAR (EAST)
A15: ='input data'!B7 -> HOANG MINH STONE TRADING COMPANY LIMITED Lot 175 MBQH 6804 Hac Thanh Ward, Thanh Hoa Province Tax ID: 2803146553 TEL: 0392794691 hoangminh6868vn@gmail.com
A21: Per Carriage By | C21: Place Of Receipt By Pre-Carrier | E21: Country Of Origin Of Goods | H21: Country Of Final Destination
A22: By Road Truck No. | C22: ='input data'!B19 -> CHENNAI | E22: INDIA | H22: ='input data'!B23 -> VIETNAM
A24: Vessel/ Flight No. | C24: Port Of Loading | E24: Port Of Discharge | H24: Place Of Delivery
C25: ='input data'!B20 -> CHENNAI | E25: ='input data'!B21 -> HAI PHONG | H25: ='input data'!B22 -> HAI PHONG
A26: Sr. No. | B26: Description Of Goods | E26: HS CODE | F26: Quantity in | H26: Rate Per | I26: TOTAL AMOUNT
F27: SQM | H27: SQM | I27: (IN USD)
A28: 1 | B28: ='input data'!B18 -> NATURAL POLISHED GRANITE SLABS | E28: 68022390 | F28: 43.55 | H28: 20.8 | I28: =F28*H28 -> 905.84
A29: 2 | B29: NATURAL POLISHED GRANITE SLABS | E29: 68022390 | F29: 425.3 | H29: 17.05 | I29: =F29*H29 -> 7251.365
A30: Container No. | C30: Slabs | D30: Gross Weight | E30: Net Weight | H30: Round Off
A31: =UPPER('input data'!B24) -> WHSU0423098 | C31: ='input data'!B25 -> 480 | D31: 28000 kgs | E31: 27500 kgs
I33: 0
A34: Amount in Words: | I34: =SUM(I28:J33) -> 8157.205
A35: Eight Thousand One Hundred Fifty Seven Dollars and Twenty One Cents
A36: Declaration | E36: For B K EXPORTS
A37: * We declare that invoice shows the actual price of the goods described and that all particulars are true and correct. | E37: Proprietor
A39: * Thickness Variation will be -/+1mm.
E40: Authorised Signatory

Sheet Sheet1
A2: BK033
A3: long | B3: 43.55 | C3: 23 | D3: =B3*C3 -> 1001.65
A4: short | B4: 425.3 | C4: 18 | D4: =B4*C4 -> 7655.4
A5: actual | D5: =D3+D4 -> 8657.05
A6: invoice | D6: 8157.21 | E6: need to pay in company's bank account
A7: after inspection | D7: =D5-D6 -> 499.84 | E7: need to pay in vietnamese account

Sheet Peacking List
A1: PACKING LIST
A2: EXPORTER | G2: INVOICE NO. | I2: DATE
A3: B K EXPORTS | G3: =Invoice!E4 -> BK033/25-26 | I3: =Invoice!H4 -> 45983
A4: 90, Jasodanagar Cross Road, Nr. Canal, | G4: LUT/ARN NO.
A5: Opp. Baroda Express Highway, Amraiwadi, | G5: ='input data'!B5 -> AD2403250650768
A6: Ahmedabad, Gujarat, India - 380026.
A7: 09313035076, 09537651265 | G7: OTHER REFERENCE(S)
A8: GSTIN : 24AGQPJ1643Q1ZW | G8: IE CODE : AGQPJ1643Q
A9: info@bkexportsinternational.com | G9: PAN NO. : AGQPJ1643Q
A10: www.bkexportsinternational.com
A11: CONSIGNEE | G11: BUYER (if other than consignee)
A12: ='input data'!B6 -> To the Order
A14: NOTIFY PARTY
A15: =Invoice!A15 -> HOANG MINH STONE TRADING COMPANY LIMITED Lot 175 MBQH 6804 Hac Thanh Ward, Thanh Hoa Province Tax ID: 2803146553 TEL: 0392794691 hoangminh6868vn@gmail.com
G18: Country of Origin of Goods | I18: Country of Final Destination
G20: INDIA | I20: =Invoice!H22 -> VIETNAM
A21: Pre-Carriage by | D21: Place of Receipt by Pre-carrier | G21: Terms of Delivery.
D22: =Invoice!C22 -> CHENNAI | G22: ='input data'!B16 -> CNF
A23: Vessel/Flight No. | D23: Port Of Loading
D24: =Invoice!C25 -> CHENNAI
A25: Port Of Discharge | D25: Place Of Delivery | G25: Terms of Payment
A26: =Invoice!E25 -> HAI PHONG | D26: =Invoice!H25 -> HAI PHONG | G26: ='input data'!B17 -> 100% Against Documents
A28: Sr. No. | B28: HSN CODE | D28: Description Of Goods | I28: SQM
A29: 1 | B29: =Invoice!E28 -> 68022390 | D29: =Invoice!B28 -> NATURAL POLISHED GRANITE SLABS | I29: =Invoice!F28 -> 43.55
A30: 2 | B30: =Invoice!E29 -> 68022390 | D30: =Invoice!B29 -> NATURAL POLISHED GRANITE SLABS | I30: =Invoice!F29 -> 425.3
A31: TOTAL | I31: =I29+I30 -> 468.85
A33: Container No. | C33: Slabs | D33: Gross Weight | F33: Net Weight
A34: =Invoice!A31 -> WHSU0423098 | C34: ='input data'!B25 -> 480 | D34: 28000kgs | F34: 27500kgs
A36: PACKING TYPE : | C36: ='input data'!B14 -> Loose packing
A37: QUANTITY : 1X20 FT CONTAINER
A39: DECLARATION | G39: For B K EXPORTS
A40: * We declare that this invoice shows the actual price of the goods
A41: describedand that all particulars are true and correct.
A42: * Zero rated export under LUT. | G42: Authorised Signature

Sheet PO
B1: B K EXPORTS
B3: 90, Jasodanagar Cross Road, Nr. Canal, Opp. Baroda Express Highway, Amraiwadi,
B4: Ahmedabad, Gujarat, India - 380026
B5: 09313035076, 9537651265, info@bkexportsinternational.com, www.bkexportsinternational.com
B7: PURCHASE ORDER
B9: DATE: | C9: =TODAY() -> 45983
B10: REF. NO. | C10: PO033/25-26
B12: TO,
B13: SIRI GRANITES
B14: SY NO 277/AA, TELDARUPALLY VILLAGE, KHAMMAM RURAL MANDAL, KHAMMAM DIST, TELANGANA, 507170 GSTIN: 36ACAFS7174H1ZW
B16: Dear Sir/ Madam,
B18: Description | F18: RATES | H18: SQFT | J18: AMOUNT
B19: POLISHED GRANITE SLABS | F19: 111.25 | H19: 4576.22 | J19: =F19*H19 -> 509104.48
B20: POLISHED GRANITE SLABS | F20: 150.83 | H20: 468.6 | J20: =F20*H20 -> 70678.938
H21: GST 0.1% | J21: =(J19+J20)*0.001 -> 579.78341
H22: TOTAL | J22: =J19+J20+J21 -> 580363.2
B24: GRAND TOTAL | J24: =J22 -> 580363.2
B26: OTHER DETAILS
B27: Packing | D27: Loose Packing
B28: Terms
B29: Port of Delivery
B30: Port of Loading | D30: Chennai
B31: Country of Destination
B32: Weight
B33: Invoice Address: | D33: B K EXPORTS
D34: 90, Jasodanagar Cross Road, Nr. Canal, Opp. Baroda Express Highway,
D35: Amraiwadi, Ahmedabad, Gujarat, India - 380026
B36: IEC NO. AGQPJ1643Q
B37: GSTIN NO. 24AGQPJ1643Q1ZW
B38: LUT NO: | C38: ='input data'!B5 -> AD2403250650768
B39: For B K EXPORTS

Sheet Sheet2
